rstparse/__init__.py
rstparse-1.0.dist-info/LICENSE
rstparse-1.0.dist-info/METADATA
rstparse-1.0.dist-info/WHEEL
rstparse-1.0.dist-info/top_level.txt
rstparse-1.0.dist-info/RECORD
