Metadata-Version: 2.1
Name: rstparse
Version: 1.0
Summary: expand and analyze RST (reStructureText) documents with auto*-directives
Home-page: https://github.com/h-ohsaki/rstparse
Author: Hiroyuki Ohsaki
Author-email: ohsaki@lsnl.jp
License: UNKNOWN
Platform: UNKNOWN
Classifier: Programming Language :: Python :: 3
Classifier: License :: OSI Approved :: GNU General Public License v3 (GPLv3)
Classifier: Operating System :: OS Independent
